adafruit_tlc5947.py
adafruit_circuitpython_tlc5947-1.3.21.dist-info/licenses/LICENSE
adafruit_circuitpython_tlc5947-1.3.21.dist-info/METADATA
adafruit_circuitpython_tlc5947-1.3.21.dist-info/WHEEL
adafruit_circuitpython_tlc5947-1.3.21.dist-info/top_level.txt
adafruit_circuitpython_tlc5947-1.3.21.dist-info/RECORD
