Metadata-Version: 2.4
Name: adafruit-circuitpython-tlc5947
Version: 1.3.21
Summary: CircuitPython library for TLC5947 12-bit 24 channel LED PWM driver.
Author-email: Adafruit Industries <circuitpython@adafruit.com>
License: MIT
Project-URL: Homepage, https://github.com/adafruit/Adafruit_CircuitPython_TLC5947
Keywords: adafruit,tlc5947,12-bit,24-channel,led,pwm,hardware,micropython,circuitpython
Classifier: Intended Audience :: Developers
Classifier: Topic :: Software Development :: Libraries
Classifier: Topic :: Software Development :: Embedded Systems
Classifier: Topic :: System :: Hardware
Classifier: License :: OSI Approved :: MIT License
Classifier: Programming Language :: Python :: 3
License-File: LICENSE
Requires-Dist: Adafruit-Blinka
Provides-Extra: optional
Dynamic: license-file
